asyncoptoma/__init__.py
asyncoptoma-0.1.0.dist-info/WHEEL
asyncoptoma-0.1.0.dist-info/METADATA
asyncoptoma-0.1.0.dist-info/RECORD
